MANIFEST.in
README.md
setup.py
yubikey.py
python_yubikey.egg-info/PKG-INFO
python_yubikey.egg-info/SOURCES.txt
python_yubikey.egg-info/dependency_links.txt
python_yubikey.egg-info/not-zip-safe
python_yubikey.egg-info/requires.txt
python_yubikey.egg-info/top_level.txt