Metadata-Version: 1.1
Name: python-yubikey
Version: 0.3.0
Summary: Simple Yubico API Wrappers
Home-page: http://github.com/fmartingr/python-yubikey
Author: Felipe Martin
Author-email: fmartingr@me.com
License: GPLv2
Platform: UNKNOWN
Classifier: Development Status :: 3 - Alpha
Classifier: Intended Audience :: Developers
Classifier: Operating System :: OS Independent
Classifier: Programming Language :: Python
